prettyPlot/__init__.py
prettyPlot/parser.py
prettyPlot/plotting.py
prettyPlot/progressBar.py
prettyPlot/version.py
prettyPlot-0.0.36.dist-info/LICENSE
prettyPlot-0.0.36.dist-info/METADATA
prettyPlot-0.0.36.dist-info/WHEEL
prettyPlot-0.0.36.dist-info/top_level.txt
prettyPlot-0.0.36.dist-info/RECORD
