Metadata-Version: 2.1
Name: prettyPlot
Version: 0.0.36
Summary: Plotting tools for journal quality figures
Home-page: https://github.com/malihass/prettyPlot
Author: Malik Hassanaly
License: BSD 3-Clause
Classifier: Intended Audience :: Science/Research
Classifier: License :: OSI Approved :: BSD License
Classifier: Natural Language :: English
Classifier: Programming Language :: Python :: 3.9
Classifier: Programming Language :: Python :: 3.10
Classifier: Programming Language :: Python :: 3.11
Classifier: Programming Language :: Python :: 3.12
Requires-Python: >=3.9
License-File: LICENSE
Requires-Dist: numpy
Requires-Dist: matplotlib >=3.7.3
Requires-Dist: imageio
